LICENSE.txt
README.md
setup.cfg
setup.py
mung/__init__.py
mung/constants.py
mung/dataset.py
mung/grammar.py
mung/graph.py
mung/io.py
mung/mungmatcher.py
mung/node.py
mung/node_class.py
mung/stafflines.py
mung/utils.py
mung.egg-info/PKG-INFO
mung.egg-info/SOURCES.txt
mung.egg-info/dependency_links.txt
mung.egg-info/requires.txt
mung.egg-info/top_level.txt
mung2midi/__init__.py
mung2midi/inference.py
mung2midi/run_inference.py
scripts/add_staff_relationships.py
scripts/add_staffline_symbols.py
scripts/analyze_agreement.py
scripts/analyze_annotations.py
scripts/analyze_tracking_log.py
scripts/baseline_process_symbols.py
scripts/get_images_from_muscima.py
scripts/infer_pitches.py
scripts/strip_staffline_symbols.py
test/test_grammar.py
test/test_node.py
test/test_node_class.py