Metadata-Version: 2.1
Name: mung
Version: 1.2.1
Summary: Tools for the Music Notation Graph representation of music notation, used primarily for optical music recognition.
Home-page: https://mung.readthedocs.io
Author: Jan Hajič jr. and Alexander Pacha
Author-email: alexander.pacha@tuwien.ac.at
License: MIT Software License
Platform: any
Classifier: Programming Language :: Python
Classifier: Development Status :: 4 - Beta
Classifier: Natural Language :: English
Classifier: Environment :: Web Environment
Classifier: Intended Audience :: Science/Research
Classifier: License :: OSI Approved :: MIT License
Classifier: Operating System :: OS Independent
Classifier: Topic :: Scientific/Engineering :: Interface Engine/Protocol Translator
License-File: LICENSE.txt
Requires-Dist: numpy
Requires-Dist: lxml
Requires-Dist: scikit-image
